[
    {
        "lon": 14.1217,
        "lat": 13.3285,
        "location_name": "Lake Chad, Nigeria (general), Nigeria",
        "category": "Majeur : Affrontement Arm\u00e9",
        "criticite_score": 5,
        "color": [
            211,
            47,
            47,
            220
        ],
        "radius": 100000,
        "url": "https://ict.org.il/african-continent-seething-with-terrorism-snapshot/",
        "sources": 2,
        "reliability": "Standard (\u00c0 corroborer) \ud83d\udfe1",
        "verification_status": "\ud83d\udce1 Signal M\u00e9dia Sp\u00e9culatif"
    },
    {
        "lon": 14.1217,
        "lat": 13.3285,
        "location_name": "Lake Chad, Nigeria (general), Nigeria",
        "category": "Majeur : Affrontement Arm\u00e9",
        "criticite_score": 5,
        "color": [
            211,
            47,
            47,
            220
        ],
        "radius": 100000,
        "url": "https://ict.org.il/african-continent-seething-with-terrorism-snapshot/",
        "sources": 2,
        "reliability": "Standard (\u00c0 corroborer) \ud83d\udfe1",
        "verification_status": "\ud83d\udce1 Signal M\u00e9dia Sp\u00e9culatif"
    },
    {
        "lon": 14.1217,
        "lat": 13.3285,
        "location_name": "Lake Chad, Nigeria (general), Nigeria",
        "category": "Majeur : Affrontement Arm\u00e9",
        "criticite_score": 5,
        "color": [
            211,
            47,
            47,
            220
        ],
        "radius": 100000,
        "url": "https://ict.org.il/african-continent-seething-with-terrorism-snapshot/",
        "sources": 4,
        "reliability": "Standard (\u00c0 corroborer) \ud83d\udfe1",
        "verification_status": "\ud83d\udce1 Signal M\u00e9dia Sp\u00e9culatif"
    },
    {
        "lon": 14.1217,
        "lat": 13.3285,
        "location_name": "Lake Chad, Nigeria (general), Nigeria",
        "category": "Majeur : Affrontement Arm\u00e9",
        "criticite_score": 5,
        "color": [
            211,
            47,
            47,
            220
        ],
        "radius": 100000,
        "url": "https://ict.org.il/african-continent-seething-with-terrorism-snapshot/",
        "sources": 2,
        "reliability": "Standard (\u00c0 corroborer) \ud83d\udfe1",
        "verification_status": "\ud83d\udce1 Signal M\u00e9dia Sp\u00e9culatif"
    },
    {
        "lon": 30.0,
        "lat": -2.0,
        "location_name": "Rwanda",
        "category": "Majeur : Affrontement Arm\u00e9",
        "criticite_score": 5,
        "color": [
            211,
            47,
            47,
            220
        ],
        "radius": 100000,
        "url": "https://ict.org.il/african-continent-seething-with-terrorism-snapshot/",
        "sources": 1,
        "reliability": "Standard (\u00c0 corroborer) \ud83d\udfe1",
        "verification_status": "\ud83d\udce1 Signal M\u00e9dia Sp\u00e9culatif"
    },
    {
        "lon": 5.08333,
        "lat": 7.16667,
        "location_name": "Ondo State, Ondo, Nigeria",
        "category": "Critique : Incident S\u00e9curitaire",
        "criticite_score": 4,
        "color": [
            244,
            67,
            54,
            200
        ],
        "radius": 80000,
        "url": "https://dailytrust.com/gunmen-invade-ondo-community-kidnap-monarch-shoot-wife/",
        "sources": 5,
        "reliability": "Standard (\u00c0 corroborer) \ud83d\udfe1",
        "verification_status": "\ud83d\udce1 Signal M\u00e9dia Sp\u00e9culatif"
    },
    {
        "lon": 5.08333,
        "lat": 7.16667,
        "location_name": "Ondo State, Ondo, Nigeria",
        "category": "Majeur : Affrontement Arm\u00e9",
        "criticite_score": 5,
        "color": [
            211,
            47,
            47,
            220
        ],
        "radius": 100000,
        "url": "https://dailytrust.com/gunmen-invade-ondo-community-kidnap-monarch-shoot-wife/",
        "sources": 3,
        "reliability": "Standard (\u00c0 corroborer) \ud83d\udfe1",
        "verification_status": "\ud83d\udce1 Signal M\u00e9dia Sp\u00e9culatif"
    },
    {
        "lon": 5.08333,
        "lat": 7.16667,
        "location_name": "Ondo State, Ondo, Nigeria",
        "category": "Majeur : Affrontement Arm\u00e9",
        "criticite_score": 5,
        "color": [
            211,
            47,
            47,
            220
        ],
        "radius": 100000,
        "url": "https://dailytrust.com/gunmen-invade-ondo-community-kidnap-monarch-shoot-wife/",
        "sources": 2,
        "reliability": "Standard (\u00c0 corroborer) \ud83d\udfe1",
        "verification_status": "\ud83d\udce1 Signal M\u00e9dia Sp\u00e9culatif"
    },
    {
        "lon": 6.28493,
        "lat": 12.3337,
        "location_name": "Kwara, Zamfara, Nigeria",
        "category": "Majeur : Affrontement Arm\u00e9",
        "criticite_score": 5,
        "color": [
            211,
            47,
            47,
            220
        ],
        "radius": 100000,
        "url": "https://dailytrust.com/gunmen-invade-ondo-community-kidnap-monarch-shoot-wife/",
        "sources": 5,
        "reliability": "Standard (\u00c0 corroborer) \ud83d\udfe1",
        "verification_status": "\ud83d\udce1 Signal M\u00e9dia Sp\u00e9culatif"
    },
    {
        "lon": 5.08333,
        "lat": 7.16667,
        "location_name": "Ondo State, Ondo, Nigeria",
        "category": "Majeur : Affrontement Arm\u00e9",
        "criticite_score": 5,
        "color": [
            211,
            47,
            47,
            220
        ],
        "radius": 100000,
        "url": "https://dailytrust.com/gunmen-invade-ondo-community-kidnap-monarch-shoot-wife/",
        "sources": 5,
        "reliability": "Standard (\u00c0 corroborer) \ud83d\udfe1",
        "verification_status": "\ud83d\udce1 Signal M\u00e9dia Sp\u00e9culatif"
    },
    {
        "lon": 14.1217,
        "lat": 13.3285,
        "location_name": "Lake Chad, Nigeria (general), Nigeria",
        "category": "Majeur : Affrontement Arm\u00e9",
        "criticite_score": 5,
        "color": [
            211,
            47,
            47,
            220
        ],
        "radius": 100000,
        "url": "https://punchng.com/military-airstrikes-kill-27-terrorists-in-borno-hideouts/",
        "sources": 10,
        "reliability": "Standard (\u00c0 corroborer) \ud83d\udfe1",
        "verification_status": "\ud83d\udce1 Signal M\u00e9dia Sp\u00e9culatif"
    },
    {
        "lon": 6.24395,
        "lat": 12.5657,
        "location_name": "Maradun, Zamfara, Nigeria",
        "category": "Majeur : Affrontement Arm\u00e9",
        "criticite_score": 5,
        "color": [
            211,
            47,
            47,
            220
        ],
        "radius": 100000,
        "url": "https://www.surinametimes.com/artikel/gunmen-kill-17-farmers-in-northern-nigeria",
        "sources": 5,
        "reliability": "Standard (\u00c0 corroborer) \ud83d\udfe1",
        "verification_status": "\ud83d\udce1 Signal M\u00e9dia Sp\u00e9culatif"
    },
    {
        "lon": 6.25,
        "lat": 12.1667,
        "location_name": "Zamfara State, Zamfara, Nigeria",
        "category": "Majeur : Affrontement Arm\u00e9",
        "criticite_score": 5,
        "color": [
            211,
            47,
            47,
            220
        ],
        "radius": 100000,
        "url": "https://www.surinametimes.com/artikel/gunmen-kill-17-farmers-in-northern-nigeria",
        "sources": 10,
        "reliability": "Standard (\u00c0 corroborer) \ud83d\udfe1",
        "verification_status": "\ud83d\udce1 Signal M\u00e9dia Sp\u00e9culatif"
    },
    {
        "lon": 5.23902,
        "lat": 13.0609,
        "location_name": "Sokoto, Sokoto, Nigeria",
        "category": "Critique : Incident S\u00e9curitaire",
        "criticite_score": 4,
        "color": [
            244,
            67,
            54,
            200
        ],
        "radius": 80000,
        "url": "https://dailypost.ng/2026/06/14/we-cant-continue-like-this-peter-obi-on-death-of-gen-abubakar-in-bandits-captivity/",
        "sources": 3,
        "reliability": "Standard (\u00c0 corroborer) \ud83d\udfe1",
        "verification_status": "\ud83d\udce1 Signal M\u00e9dia Sp\u00e9culatif"
    },
    {
        "lon": 4.56667,
        "lat": 7.76667,
        "location_name": "Osogbo, Osun, Nigeria",
        "category": "Critique : Incident S\u00e9curitaire",
        "criticite_score": 4,
        "color": [
            244,
            67,
            54,
            200
        ],
        "radius": 80000,
        "url": "https://dailypost.ng/2026/06/14/nigeria-will-overcome-insecurity-osun-apc-chieftain-oyintiloye/",
        "sources": 5,
        "reliability": "Standard (\u00c0 corroborer) \ud83d\udfe1",
        "verification_status": "\ud83d\udce1 Signal M\u00e9dia Sp\u00e9culatif"
    },
    {
        "lon": 8.51667,
        "lat": 11.9964,
        "location_name": "Kano, Kano, Nigeria",
        "category": "Majeur : Affrontement Arm\u00e9",
        "criticite_score": 5,
        "color": [
            211,
            47,
            47,
            220
        ],
        "radius": 100000,
        "url": "https://dailypost.ng/2026/06/14/ndlea-intercepts-businessman-with-6-10kg-of-liquid-cocaine-from-brazil/",
        "sources": 4,
        "reliability": "Standard (\u00c0 corroborer) \ud83d\udfe1",
        "verification_status": "\ud83d\udce1 Signal M\u00e9dia Sp\u00e9culatif"
    },
    {
        "lon": 6.28493,
        "lat": 12.3337,
        "location_name": "Kwara, Zamfara, Nigeria",
        "category": "Majeur : Affrontement Arm\u00e9",
        "criticite_score": 5,
        "color": [
            211,
            47,
            47,
            220
        ],
        "radius": 100000,
        "url": "https://dailypost.ng/2026/06/14/ndlea-intercepts-businessman-with-6-10kg-of-liquid-cocaine-from-brazil/",
        "sources": 1,
        "reliability": "Standard (\u00c0 corroborer) \ud83d\udfe1",
        "verification_status": "\ud83d\udce1 Signal M\u00e9dia Sp\u00e9culatif"
    },
    {
        "lon": 10.5,
        "lat": 8.0,
        "location_name": "Taraba State, Taraba, Nigeria",
        "category": "Majeur : Affrontement Arm\u00e9",
        "criticite_score": 5,
        "color": [
            211,
            47,
            47,
            220
        ],
        "radius": 100000,
        "url": "https://dailypost.ng/2026/06/14/ndlea-intercepts-businessman-with-6-10kg-of-liquid-cocaine-from-brazil/",
        "sources": 3,
        "reliability": "Standard (\u00c0 corroborer) \ud83d\udfe1",
        "verification_status": "\ud83d\udce1 Signal M\u00e9dia Sp\u00e9culatif"
    },
    {
        "lon": 8.51667,
        "lat": 11.9964,
        "location_name": "Kano, Kano, Nigeria",
        "category": "Majeur : Affrontement Arm\u00e9",
        "criticite_score": 5,
        "color": [
            211,
            47,
            47,
            220
        ],
        "radius": 100000,
        "url": "https://dailypost.ng/2026/06/14/ndlea-intercepts-businessman-with-6-10kg-of-liquid-cocaine-from-brazil/",
        "sources": 1,
        "reliability": "Standard (\u00c0 corroborer) \ud83d\udfe1",
        "verification_status": "\ud83d\udce1 Signal M\u00e9dia Sp\u00e9culatif"
    },
    {
        "lon": 10.5,
        "lat": 8.0,
        "location_name": "Taraba State, Taraba, Nigeria",
        "category": "Majeur : Affrontement Arm\u00e9",
        "criticite_score": 5,
        "color": [
            211,
            47,
            47,
            220
        ],
        "radius": 100000,
        "url": "https://dailypost.ng/2026/06/14/ndlea-intercepts-businessman-with-6-10kg-of-liquid-cocaine-from-brazil/",
        "sources": 1,
        "reliability": "Standard (\u00c0 corroborer) \ud83d\udfe1",
        "verification_status": "\ud83d\udce1 Signal M\u00e9dia Sp\u00e9culatif"
    },
    {
        "lon": 4.56667,
        "lat": 7.76667,
        "location_name": "Osogbo, Osun, Nigeria",
        "category": "Majeur : Affrontement Arm\u00e9",
        "criticite_score": 5,
        "color": [
            211,
            47,
            47,
            220
        ],
        "radius": 100000,
        "url": "https://saharareporters.com/2026/06/14/governor-adeleke-accuses-osun-apc-sponsoring-assassination-attempt-prominent-monarch",
        "sources": 8,
        "reliability": "Standard (\u00c0 corroborer) \ud83d\udfe1",
        "verification_status": "\ud83d\udce1 Signal M\u00e9dia Sp\u00e9culatif"
    },
    {
        "lon": 4.56667,
        "lat": 7.76667,
        "location_name": "Osogbo, Osun, Nigeria",
        "category": "Majeur : Affrontement Arm\u00e9",
        "criticite_score": 5,
        "color": [
            211,
            47,
            47,
            220
        ],
        "radius": 100000,
        "url": "https://saharareporters.com/2026/06/14/governor-adeleke-accuses-osun-apc-sponsoring-assassination-attempt-prominent-monarch",
        "sources": 2,
        "reliability": "Standard (\u00c0 corroborer) \ud83d\udfe1",
        "verification_status": "\ud83d\udce1 Signal M\u00e9dia Sp\u00e9culatif"
    },
    {
        "lon": 7.5,
        "lat": 12.25,
        "location_name": "Katsina State, Katsina, Nigeria",
        "category": "Critique : Incident S\u00e9curitaire",
        "criticite_score": 4,
        "color": [
            244,
            67,
            54,
            200
        ],
        "radius": 80000,
        "url": "https://saharareporters.com/2026/06/14/nigerian-herders-group-macban-condemns-banditry-after-ex-general-rabe-abubakar-dies",
        "sources": 10,
        "reliability": "Standard (\u00c0 corroborer) \ud83d\udfe1",
        "verification_status": "\ud83d\udce1 Signal M\u00e9dia Sp\u00e9culatif"
    },
    {
        "lon": 10.8333,
        "lat": 7.16667,
        "location_name": "Maihula, Nigeria (general), Nigeria",
        "category": "Majeur : Affrontement Arm\u00e9",
        "criticite_score": 5,
        "color": [
            211,
            47,
            47,
            220
        ],
        "radius": 100000,
        "url": "https://saharareporters.com/2026/06/14/nigerias-anti-narcotics-agency-arrests-two-persons-living-disability-separate-abia",
        "sources": 1,
        "reliability": "Standard (\u00c0 corroborer) \ud83d\udfe1",
        "verification_status": "\ud83d\udce1 Signal M\u00e9dia Sp\u00e9culatif"
    },
    {
        "lon": 10.5,
        "lat": 8.0,
        "location_name": "Taraba State, Taraba, Nigeria",
        "category": "Majeur : Affrontement Arm\u00e9",
        "criticite_score": 5,
        "color": [
            211,
            47,
            47,
            220
        ],
        "radius": 100000,
        "url": "https://saharareporters.com/2026/06/14/nigerias-anti-narcotics-agency-arrests-two-persons-living-disability-separate-abia",
        "sources": 1,
        "reliability": "Standard (\u00c0 corroborer) \ud83d\udfe1",
        "verification_status": "\ud83d\udce1 Signal M\u00e9dia Sp\u00e9culatif"
    },
    {
        "lon": 7.53333,
        "lat": 9.08333,
        "location_name": "Abuja, Abuja Federal Capital Territory, Nigeria",
        "category": "Critique : Incident S\u00e9curitaire",
        "criticite_score": 5,
        "color": [
            244,
            67,
            54,
            235
        ],
        "radius": 100000,
        "url": "https://saharareporters.com/2026/06/14/nigerian-herders-group-macban-condemns-banditry-after-ex-general-rabe-abubakar-dies",
        "sources": 7,
        "reliability": "Standard (\u00c0 corroborer) \ud83d\udfe1",
        "verification_status": "\ud83d\udce1 Signal M\u00e9dia Sp\u00e9culatif"
    },
    {
        "lon": 30.0,
        "lat": -2.0,
        "location_name": "Rwanda",
        "category": "Majeur : Affrontement Arm\u00e9",
        "criticite_score": 5,
        "color": [
            211,
            47,
            47,
            220
        ],
        "radius": 100000,
        "url": "https://capitalethiopia.com/2026/06/14/beyond-borders/",
        "sources": 5,
        "reliability": "Standard (\u00c0 corroborer) \ud83d\udfe1",
        "verification_status": "\ud83d\udce1 Signal M\u00e9dia Sp\u00e9culatif"
    },
    {
        "lon": 12.0,
        "lat": 6.0,
        "location_name": "Cameroon",
        "category": "Majeur : Affrontement Arm\u00e9",
        "criticite_score": 5,
        "color": [
            211,
            47,
            47,
            220
        ],
        "radius": 100000,
        "url": "https://www.mirror.co.uk/news/uk-news/royal-marines-shadow-fleet-raid-37293200",
        "sources": 10,
        "reliability": "Standard (\u00c0 corroborer) \ud83d\udfe1",
        "verification_status": "\ud83d\udce1 Signal M\u00e9dia Sp\u00e9culatif"
    },
    {
        "lon": 4.65775,
        "lat": 10.7592,
        "location_name": "Pissa, Niger, Nigeria",
        "category": "Majeur : Affrontement Arm\u00e9",
        "criticite_score": 5,
        "color": [
            211,
            47,
            47,
            220
        ],
        "radius": 100000,
        "url": "https://theeagleonline.com.ng/bandits-kill-three-burn-houses-in-niger-police/",
        "sources": 6,
        "reliability": "Standard (\u00c0 corroborer) \ud83d\udfe1",
        "verification_status": "\ud83d\udce1 Signal M\u00e9dia Sp\u00e9culatif"
    },
    {
        "lon": 9.75,
        "lat": 9.16667,
        "location_name": "Plateau State, Plateau, Nigeria",
        "category": "Majeur : Affrontement Arm\u00e9",
        "criticite_score": 5,
        "color": [
            211,
            47,
            47,
            220
        ],
        "radius": 100000,
        "url": "https://www.theblaze.com/lifestyle/5-countries-where-christians-face-brutal-persecution-and-how-you-can-help",
        "sources": 5,
        "reliability": "Standard (\u00c0 corroborer) \ud83d\udfe1",
        "verification_status": "\ud83d\udce1 Signal M\u00e9dia Sp\u00e9culatif"
    },
    {
        "lon": 7.60063,
        "lat": 12.9894,
        "location_name": "Katsina, Katsina, Nigeria",
        "category": "Critique : Incident S\u00e9curitaire",
        "criticite_score": 4,
        "color": [
            244,
            67,
            54,
            200
        ],
        "radius": 80000,
        "url": "https://theeagleonline.com.ng/general-rabe-buried-after-release-of-remains-by-kidnappers/",
        "sources": 8,
        "reliability": "Standard (\u00c0 corroborer) \ud83d\udfe1",
        "verification_status": "\ud83d\udce1 Signal M\u00e9dia Sp\u00e9culatif"
    },
    {
        "lon": 9.75,
        "lat": 9.16667,
        "location_name": "Plateau State, Plateau, Nigeria",
        "category": "Majeur : Affrontement Arm\u00e9",
        "criticite_score": 5,
        "color": [
            211,
            47,
            47,
            220
        ],
        "radius": 100000,
        "url": "https://www.theblaze.com/lifestyle/5-countries-where-christians-face-brutal-persecution-and-how-you-can-help",
        "sources": 10,
        "reliability": "Standard (\u00c0 corroborer) \ud83d\udfe1",
        "verification_status": "\ud83d\udce1 Signal M\u00e9dia Sp\u00e9culatif"
    },
    {
        "lon": 4.65775,
        "lat": 10.7592,
        "location_name": "Pissa, Niger, Nigeria",
        "category": "Majeur : Affrontement Arm\u00e9",
        "criticite_score": 5,
        "color": [
            211,
            47,
            47,
            220
        ],
        "radius": 100000,
        "url": "https://theeagleonline.com.ng/bandits-kill-three-burn-houses-in-niger-police/",
        "sources": 3,
        "reliability": "Standard (\u00c0 corroborer) \ud83d\udfe1",
        "verification_status": "\ud83d\udce1 Signal M\u00e9dia Sp\u00e9culatif"
    },
    {
        "lon": 7.60063,
        "lat": 12.9894,
        "location_name": "Katsina, Katsina, Nigeria",
        "category": "Critique : Incident S\u00e9curitaire",
        "criticite_score": 4,
        "color": [
            244,
            67,
            54,
            200
        ],
        "radius": 80000,
        "url": "https://theeagleonline.com.ng/general-rabe-buried-after-release-of-remains-by-kidnappers/",
        "sources": 2,
        "reliability": "Standard (\u00c0 corroborer) \ud83d\udfe1",
        "verification_status": "\ud83d\udce1 Signal M\u00e9dia Sp\u00e9culatif"
    },
    {
        "lon": 7.5,
        "lat": 12.25,
        "location_name": "Katsina State, Katsina, Nigeria",
        "category": "Critique : Incident S\u00e9curitaire",
        "criticite_score": 4,
        "color": [
            244,
            67,
            54,
            200
        ],
        "radius": 80000,
        "url": "https://theeagleonline.com.ng/tinubu-condemns-retired-generals-death-vows-no-talks-with-terrorists/",
        "sources": 4,
        "reliability": "Standard (\u00c0 corroborer) \ud83d\udfe1",
        "verification_status": "\ud83d\udce1 Signal M\u00e9dia Sp\u00e9culatif"
    },
    {
        "lon": 8.51667,
        "lat": 8.48333,
        "location_name": "Lafia, Nassarawa, Nigeria",
        "category": "Majeur : Affrontement Arm\u00e9",
        "criticite_score": 5,
        "color": [
            211,
            47,
            47,
            220
        ],
        "radius": 100000,
        "url": "https://leadership.ng/democracy-at-27-the-freedom-we-still-owe-ourselves/",
        "sources": 3,
        "reliability": "Standard (\u00c0 corroborer) \ud83d\udfe1",
        "verification_status": "\ud83d\udce1 Signal M\u00e9dia Sp\u00e9culatif"
    },
    {
        "lon": 8.51667,
        "lat": 8.48333,
        "location_name": "Lafia, Nassarawa, Nigeria",
        "category": "Majeur : Affrontement Arm\u00e9",
        "criticite_score": 5,
        "color": [
            211,
            47,
            47,
            220
        ],
        "radius": 100000,
        "url": "https://leadership.ng/democracy-at-27-the-freedom-we-still-owe-ourselves/",
        "sources": 1,
        "reliability": "Standard (\u00c0 corroborer) \ud83d\udfe1",
        "verification_status": "\ud83d\udce1 Signal M\u00e9dia Sp\u00e9culatif"
    },
    {
        "lon": 8.51667,
        "lat": 8.48333,
        "location_name": "Lafia, Nassarawa, Nigeria",
        "category": "Majeur : Affrontement Arm\u00e9",
        "criticite_score": 5,
        "color": [
            211,
            47,
            47,
            220
        ],
        "radius": 100000,
        "url": "https://leadership.ng/democracy-at-27-the-freedom-we-still-owe-ourselves/",
        "sources": 1,
        "reliability": "Standard (\u00c0 corroborer) \ud83d\udfe1",
        "verification_status": "\ud83d\udce1 Signal M\u00e9dia Sp\u00e9culatif"
    },
    {
        "lon": 7.5,
        "lat": 12.25,
        "location_name": "Katsina State, Katsina, Nigeria",
        "category": "Critique : Incident S\u00e9curitaire",
        "criticite_score": 4,
        "color": [
            244,
            67,
            54,
            200
        ],
        "radius": 80000,
        "url": "https://www.channelafrica.co.za/channelafrica/news/kidnapped-retired-nigerian-general-dies-in-captivity/",
        "sources": 4,
        "reliability": "Standard (\u00c0 corroborer) \ud83d\udfe1",
        "verification_status": "\ud83d\udce1 Signal M\u00e9dia Sp\u00e9culatif"
    },
    {
        "lon": 7.5,
        "lat": 12.25,
        "location_name": "Katsina State, Katsina, Nigeria",
        "category": "Critique : Incident S\u00e9curitaire",
        "criticite_score": 4,
        "color": [
            244,
            67,
            54,
            200
        ],
        "radius": 80000,
        "url": "https://www.channelafrica.co.za/channelafrica/news/kidnapped-retired-nigerian-general-dies-in-captivity/",
        "sources": 6,
        "reliability": "Standard (\u00c0 corroborer) \ud83d\udfe1",
        "verification_status": "\ud83d\udce1 Signal M\u00e9dia Sp\u00e9culatif"
    },
    {
        "lon": 5.23902,
        "lat": 13.0609,
        "location_name": "Sokoto, Sokoto, Nigeria",
        "category": "Critique : Incident S\u00e9curitaire",
        "criticite_score": 4,
        "color": [
            244,
            67,
            54,
            200
        ],
        "radius": 80000,
        "url": "https://www.nationalaccordnewspaper.com/nigeria-cannot-continue-like-this-peter-obi-condemns-rising-insecurity-mourns-death-of-retired-general-in-kidnappers-custody/",
        "sources": 1,
        "reliability": "Standard (\u00c0 corroborer) \ud83d\udfe1",
        "verification_status": "\ud83d\udce1 Signal M\u00e9dia Sp\u00e9culatif"
    },
    {
        "lon": 5.23902,
        "lat": 13.0609,
        "location_name": "Sokoto, Sokoto, Nigeria",
        "category": "Critique : Incident S\u00e9curitaire",
        "criticite_score": 4,
        "color": [
            244,
            67,
            54,
            200
        ],
        "radius": 80000,
        "url": "https://www.nationalaccordnewspaper.com/nigeria-cannot-continue-like-this-peter-obi-condemns-rising-insecurity-mourns-death-of-retired-general-in-kidnappers-custody/",
        "sources": 1,
        "reliability": "Standard (\u00c0 corroborer) \ud83d\udfe1",
        "verification_status": "\ud83d\udce1 Signal M\u00e9dia Sp\u00e9culatif"
    },
    {
        "lon": 3.36667,
        "lat": 6.51667,
        "location_name": "Tinubu, Lagos, Nigeria",
        "category": "Critique : Incident S\u00e9curitaire",
        "criticite_score": 4,
        "color": [
            244,
            67,
            54,
            200
        ],
        "radius": 80000,
        "url": "https://www.nationalaccordnewspaper.com/unravelling-the-terror-empire-by-chidi-amuta/",
        "sources": 5,
        "reliability": "Standard (\u00c0 corroborer) \ud83d\udfe1",
        "verification_status": "\ud83d\udce1 Signal M\u00e9dia Sp\u00e9culatif"
    },
    {
        "lon": 3.36667,
        "lat": 6.51667,
        "location_name": "Tinubu, Lagos, Nigeria",
        "category": "Majeur : Affrontement Arm\u00e9",
        "criticite_score": 5,
        "color": [
            211,
            47,
            47,
            220
        ],
        "radius": 100000,
        "url": "https://www.nationalaccordnewspaper.com/unravelling-the-terror-empire-by-chidi-amuta/",
        "sources": 5,
        "reliability": "Standard (\u00c0 corroborer) \ud83d\udfe1",
        "verification_status": "\ud83d\udce1 Signal M\u00e9dia Sp\u00e9culatif"
    },
    {
        "lon": 7.5,
        "lat": 12.25,
        "location_name": "Katsina State, Katsina, Nigeria",
        "category": "Majeur : Affrontement Arm\u00e9",
        "criticite_score": 5,
        "color": [
            211,
            47,
            47,
            220
        ],
        "radius": 100000,
        "url": "https://promptnewsonline.com/we-wont-release-bandits-held-by-our-security-agencies-tinubu-vows/",
        "sources": 4,
        "reliability": "Standard (\u00c0 corroborer) \ud83d\udfe1",
        "verification_status": "\ud83d\udce1 Signal M\u00e9dia Sp\u00e9culatif"
    },
    {
        "lon": 7.5,
        "lat": 12.25,
        "location_name": "Katsina State, Katsina, Nigeria",
        "category": "Majeur : Affrontement Arm\u00e9",
        "criticite_score": 5,
        "color": [
            211,
            47,
            47,
            220
        ],
        "radius": 100000,
        "url": "https://promptnewsonline.com/we-wont-release-bandits-held-by-our-security-agencies-tinubu-vows/",
        "sources": 4,
        "reliability": "Standard (\u00c0 corroborer) \ud83d\udfe1",
        "verification_status": "\ud83d\udce1 Signal M\u00e9dia Sp\u00e9culatif"
    },
    {
        "lon": 7.5,
        "lat": 12.25,
        "location_name": "Katsina State, Katsina, Nigeria",
        "category": "Majeur : Affrontement Arm\u00e9",
        "criticite_score": 5,
        "color": [
            211,
            47,
            47,
            220
        ],
        "radius": 100000,
        "url": "https://promptnewsonline.com/we-wont-release-bandits-held-by-our-security-agencies-tinubu-vows/",
        "sources": 4,
        "reliability": "Standard (\u00c0 corroborer) \ud83d\udfe1",
        "verification_status": "\ud83d\udce1 Signal M\u00e9dia Sp\u00e9culatif"
    },
    {
        "lon": 7.5,
        "lat": 12.25,
        "location_name": "Katsina State, Katsina, Nigeria",
        "category": "Majeur : Affrontement Arm\u00e9",
        "criticite_score": 5,
        "color": [
            211,
            47,
            47,
            220
        ],
        "radius": 100000,
        "url": "https://promptnewsonline.com/we-wont-release-bandits-held-by-our-security-agencies-tinubu-vows/",
        "sources": 4,
        "reliability": "Standard (\u00c0 corroborer) \ud83d\udfe1",
        "verification_status": "\ud83d\udce1 Signal M\u00e9dia Sp\u00e9culatif"
    },
    {
        "lon": 7.5,
        "lat": 12.25,
        "location_name": "Katsina State, Katsina, Nigeria",
        "category": "Critique : Incident S\u00e9curitaire",
        "criticite_score": 4,
        "color": [
            244,
            67,
            54,
            200
        ],
        "radius": 80000,
        "url": "https://blueprint.ng/senate-mourns-ex-defence-spokesman-general-rabe-abubakar/",
        "sources": 10,
        "reliability": "Standard (\u00c0 corroborer) \ud83d\udfe1",
        "verification_status": "\ud83d\udce1 Signal M\u00e9dia Sp\u00e9culatif"
    },
    {
        "lon": 7.60063,
        "lat": 12.9894,
        "location_name": "Katsina, Katsina, Nigeria",
        "category": "Majeur : Affrontement Arm\u00e9",
        "criticite_score": 5,
        "color": [
            211,
            47,
            47,
            220
        ],
        "radius": 100000,
        "url": "https://blueprint.ng/tinubu-shocked-over-demise-of-general-rabe-abubakar/",
        "sources": 2,
        "reliability": "Standard (\u00c0 corroborer) \ud83d\udfe1",
        "verification_status": "\ud83d\udce1 Signal M\u00e9dia Sp\u00e9culatif"
    },
    {
        "lon": 7.60063,
        "lat": 12.9894,
        "location_name": "Katsina, Katsina, Nigeria",
        "category": "Majeur : Affrontement Arm\u00e9",
        "criticite_score": 5,
        "color": [
            211,
            47,
            47,
            220
        ],
        "radius": 100000,
        "url": "https://blueprint.ng/tinubu-shocked-over-demise-of-general-rabe-abubakar/",
        "sources": 2,
        "reliability": "Standard (\u00c0 corroborer) \ud83d\udfe1",
        "verification_status": "\ud83d\udce1 Signal M\u00e9dia Sp\u00e9culatif"
    },
    {
        "lon": 7.60063,
        "lat": 12.9894,
        "location_name": "Katsina, Katsina, Nigeria",
        "category": "Majeur : Affrontement Arm\u00e9",
        "criticite_score": 5,
        "color": [
            211,
            47,
            47,
            220
        ],
        "radius": 100000,
        "url": "https://blueprint.ng/tinubu-shocked-over-demise-of-general-rabe-abubakar/",
        "sources": 2,
        "reliability": "Standard (\u00c0 corroborer) \ud83d\udfe1",
        "verification_status": "\ud83d\udce1 Signal M\u00e9dia Sp\u00e9culatif"
    },
    {
        "lon": 7.60063,
        "lat": 12.9894,
        "location_name": "Katsina, Katsina, Nigeria",
        "category": "Majeur : Affrontement Arm\u00e9",
        "criticite_score": 5,
        "color": [
            211,
            47,
            47,
            220
        ],
        "radius": 100000,
        "url": "https://blueprint.ng/tinubu-shocked-over-demise-of-general-rabe-abubakar/",
        "sources": 2,
        "reliability": "Standard (\u00c0 corroborer) \ud83d\udfe1",
        "verification_status": "\ud83d\udce1 Signal M\u00e9dia Sp\u00e9culatif"
    },
    {
        "lon": 7.5297,
        "lat": 11.6035,
        "location_name": "Tsiga, Katsina, Nigeria",
        "category": "Critique : Incident S\u00e9curitaire",
        "criticite_score": 4,
        "color": [
            244,
            67,
            54,
            200
        ],
        "radius": 80000,
        "url": "https://dailypost.ng/2026/06/14/rabes-death-end-negotiations-with-bandits-now-galma-other-experts-tell-govt/",
        "sources": 1,
        "reliability": "Standard (\u00c0 corroborer) \ud83d\udfe1",
        "verification_status": "\ud83d\udce1 Signal M\u00e9dia Sp\u00e9culatif"
    },
    {
        "lon": 7.5297,
        "lat": 11.6035,
        "location_name": "Tsiga, Katsina, Nigeria",
        "category": "Critique : Incident S\u00e9curitaire",
        "criticite_score": 4,
        "color": [
            244,
            67,
            54,
            200
        ],
        "radius": 80000,
        "url": "https://dailypost.ng/2026/06/14/rabes-death-end-negotiations-with-bandits-now-galma-other-experts-tell-govt/",
        "sources": 2,
        "reliability": "Standard (\u00c0 corroborer) \ud83d\udfe1",
        "verification_status": "\ud83d\udce1 Signal M\u00e9dia Sp\u00e9culatif"
    },
    {
        "lon": 7.5297,
        "lat": 11.6035,
        "location_name": "Tsiga, Katsina, Nigeria",
        "category": "Majeur : Affrontement Arm\u00e9",
        "criticite_score": 5,
        "color": [
            211,
            47,
            47,
            220
        ],
        "radius": 100000,
        "url": "https://dailypost.ng/2026/06/14/rabes-death-end-negotiations-with-bandits-now-galma-other-experts-tell-govt/",
        "sources": 2,
        "reliability": "Standard (\u00c0 corroborer) \ud83d\udfe1",
        "verification_status": "\ud83d\udce1 Signal M\u00e9dia Sp\u00e9culatif"
    },
    {
        "lon": 7.5297,
        "lat": 11.6035,
        "location_name": "Tsiga, Katsina, Nigeria",
        "category": "Critique : Incident S\u00e9curitaire",
        "criticite_score": 4,
        "color": [
            244,
            67,
            54,
            200
        ],
        "radius": 80000,
        "url": "https://dailypost.ng/2026/06/14/rabes-death-end-negotiations-with-bandits-now-galma-other-experts-tell-govt/",
        "sources": 4,
        "reliability": "Standard (\u00c0 corroborer) \ud83d\udfe1",
        "verification_status": "\ud83d\udce1 Signal M\u00e9dia Sp\u00e9culatif"
    },
    {
        "lon": -2.0,
        "lat": 8.0,
        "location_name": "Ghana",
        "category": "Majeur : Affrontement Arm\u00e9",
        "criticite_score": 5,
        "color": [
            211,
            47,
            47,
            220
        ],
        "radius": 100000,
        "url": "https://www.dailymail.com/news/article-15898469/Guzman-y-Gomez-gold-coast-drive-crash.html",
        "sources": 2,
        "reliability": "Standard (\u00c0 corroborer) \ud83d\udfe1",
        "verification_status": "\ud83d\udce1 Signal M\u00e9dia Sp\u00e9culatif"
    }
]