[
    {
        "Mati\u00e8re Premi\u00e8re": "\ud83d\udee2\ufe0f Brent Crude ($/bbl)",
        "Principaux producteurs": "Congo/Gabon/Tchad",
        "Cours Actuel": 75.5999984741211,
        "Cours (Il y a 1 an)": 69.58000183105469,
        "Var. (1 an)": 8.651906416564053,
        "Cours (Il y a 3 ans)": 78.47000122070312,
        "Var. globale (3 ans)": -3.6574521497838646
    },
    {
        "Mati\u00e8re Premi\u00e8re": "\ud83d\udfe1 Or ($/oz)",
        "Principaux producteurs": "RCA/Gabon",
        "Cours Actuel": 4122.39990234375,
        "Cours (Il y a 1 an)": 3332.199951171875,
        "Var. (1 an)": 23.71406166349579,
        "Cours (Il y a 3 ans)": 1926.199951171875,
        "Var. globale (3 ans)": 114.01723636405117
    },
    {
        "Mati\u00e8re Premi\u00e8re": "\ud83e\udeb5 Indice Bois ($/1k bd ft)",
        "Principaux producteurs": "Congo/Gabon/Cameroun",
        "Cours Actuel": 344.0,
        "Cours (Il y a 1 an)": 668.0,
        "Var. (1 an)": -48.50299401197605,
        "Cours (Il y a 3 ans)": 668.0,
        "Var. globale (3 ans)": -48.50299401197605
    },
    {
        "Mati\u00e8re Premi\u00e8re": "\ud83c\udf6b Cacao ($/t)",
        "Principaux producteurs": "Cameroun",
        "Cours Actuel": 5779.0,
        "Cours (Il y a 1 an)": 8879.0,
        "Var. (1 an)": -34.91384164883433,
        "Cours (Il y a 3 ans)": 3274.0,
        "Var. globale (3 ans)": 76.51191203420892
    },
    {
        "Mati\u00e8re Premi\u00e8re": "\u2615 Caf\u00e9 ($/lb)",
        "Principaux producteurs": "RCA/Cameroun",
        "Cours Actuel": 317.3999938964844,
        "Cours (Il y a 1 an)": 280.04998779296875,
        "Var. (1 an)": 13.336906885040534,
        "Cours (Il y a 3 ans)": 162.8000030517578,
        "Var. globale (3 ans)": 94.96313755938672
    }
]